{
  "id": 115,
  "name": "车主",
  "desc": null,
  "categoryId": 7,
  "categoryName": "海报",
  "width": 1242,
  "height": 2208,
  "json": {
    "objects": [
      {
        "id": "workspace",
        "rx": 0,
        "ry": 0,
        "top": 0,
        "fill": "rgba(255,255,255,1)",
        "left": 0,
        "type": "rect",
        "angle": 0,
        "flipX": false,
        "flipY": false,
        "skewX": 0,
        "skewY": 0,
        "width": 1242,
        "height": 2208,
        "scaleX": 1,
        "scaleY": 1,
        "shadow": null,
        "stroke": null,
        "evented": false,
        "opacity": 1,
        "originX": "left",
        "originY": "top",
        "version": "5.5.2",
        "visible": true,
        "fillRule": "nonzero",
        "paintFirst": "fill",
        "selectable": false,
        "hasControls": false,
        "strokeWidth": 0,
        "strokeLineCap": "butt",
        "strokeUniform": false,
        "strokeLineJoin": "miter",
        "backgroundColor": "",
        "strokeDashArray": null,
        "strokeDashOffset": 0,
        "strokeMiterLimit": 4,
        "globalCompositeOperation": "source-over"
      },
      {
        "id": "eb564fbe-c4ad-4ba0-bfaa-7d5877fb57d8",
        "src": "__LOCAL_TEMPLATE_ASSET__/e418ab88a9b5643b77f09d4dac8c41088184d545.png",
        "top": 0,
        "fill": "rgb(0,0,0)",
        "left": 0,
        "name": "背景",
        "type": "image",
        "angle": 0,
        "cropX": 0,
        "cropY": 0,
        "flipX": false,
        "flipY": false,
        "skewX": 0,
        "skewY": 0,
        "width": 1242,
        "height": 2208,
        "scaleX": 1,
        "scaleY": 1,
        "shadow": null,
        "stroke": null,
        "evented": true,
        "filters": [],
        "opacity": 1,
        "originX": "left",
        "originY": "top",
        "version": "5.5.2",
        "visible": true,
        "fillRule": "nonzero",
        "paintFirst": "fill",
        "selectable": true,
        "crossOrigin": "anonymous",
        "hasControls": true,
        "strokeWidth": 0,
        "strokeLineCap": "butt",
        "strokeUniform": false,
        "strokeLineJoin": "miter",
        "backgroundColor": "",
        "strokeDashArray": null,
        "strokeDashOffset": 0,
        "strokeMiterLimit": 4,
        "globalCompositeOperation": "source-over"
      },
      {
        "id": "5b3ea4bb-1bf3-49f6-9ec6-423593d77be9",
        "src": "__LOCAL_TEMPLATE_ASSET__/c8d0264a6efa5e3891aeb68676be06a3c5e499f8.png",
        "top": 821,
        "fill": "rgb(0,0,0)",
        "left": 0,
        "name": "图层 1",
        "type": "image",
        "angle": 0,
        "cropX": 0,
        "cropY": 0,
        "flipX": false,
        "flipY": false,
        "skewX": 0,
        "skewY": 0,
        "width": 1242,
        "height": 1387,
        "scaleX": 1,
        "scaleY": 1,
        "shadow": null,
        "stroke": null,
        "evented": true,
        "filters": [],
        "opacity": 1,
        "originX": "left",
        "originY": "top",
        "version": "5.5.2",
        "visible": true,
        "fillRule": "nonzero",
        "paintFirst": "fill",
        "selectable": true,
        "crossOrigin": "anonymous",
        "hasControls": true,
        "strokeWidth": 0,
        "strokeLineCap": "butt",
        "strokeUniform": false,
        "strokeLineJoin": "miter",
        "backgroundColor": "",
        "strokeDashArray": null,
        "strokeDashOffset": 0,
        "strokeMiterLimit": 4,
        "globalCompositeOperation": "source-over"
      },
      {
        "id": "970196f3-7d3d-4a48-9acd-a6557bf408fc",
        "src": "__LOCAL_TEMPLATE_ASSET__/c61ce0074a4e6bc777b567d0b1aa952c3c3d3c92.png",
        "top": 842,
        "fill": "rgb(0,0,0)",
        "left": 110,
        "name": "图层 2",
        "type": "image",
        "angle": 0,
        "cropX": 0,
        "cropY": 0,
        "flipX": false,
        "flipY": false,
        "skewX": 0,
        "skewY": 0,
        "width": 955,
        "height": 794,
        "scaleX": 1,
        "scaleY": 1,
        "shadow": null,
        "stroke": null,
        "evented": true,
        "filters": [],
        "opacity": 1,
        "originX": "left",
        "originY": "top",
        "version": "5.5.2",
        "visible": true,
        "fillRule": "nonzero",
        "paintFirst": "fill",
        "selectable": true,
        "crossOrigin": "anonymous",
        "hasControls": true,
        "strokeWidth": 0,
        "strokeLineCap": "butt",
        "strokeUniform": false,
        "strokeLineJoin": "miter",
        "backgroundColor": "",
        "strokeDashArray": null,
        "strokeDashOffset": 0,
        "strokeMiterLimit": 4,
        "globalCompositeOperation": "source-over"
      },
      {
        "id": "bfeed170-6e03-40cc-8634-c4d49d2f144e",
        "src": "__LOCAL_TEMPLATE_ASSET__/913c965aebdafdda5859e7f669460c46c8e1077d.png",
        "top": 551,
        "fill": "rgb(0,0,0)",
        "left": 255,
        "name": "图层 3",
        "type": "image",
        "angle": 0,
        "cropX": 0,
        "cropY": 0,
        "flipX": false,
        "flipY": false,
        "skewX": 0,
        "skewY": 0,
        "width": 698,
        "height": 641,
        "scaleX": 1,
        "scaleY": 1,
        "shadow": null,
        "stroke": null,
        "evented": true,
        "filters": [],
        "opacity": 1,
        "originX": "left",
        "originY": "top",
        "version": "5.5.2",
        "visible": true,
        "fillRule": "nonzero",
        "paintFirst": "fill",
        "selectable": true,
        "crossOrigin": "anonymous",
        "hasControls": true,
        "strokeWidth": 0,
        "strokeLineCap": "butt",
        "strokeUniform": false,
        "strokeLineJoin": "miter",
        "backgroundColor": "",
        "strokeDashArray": null,
        "strokeDashOffset": 0,
        "strokeMiterLimit": 4,
        "globalCompositeOperation": "source-over"
      },
      {
        "id": "e87097dc-f11f-4792-a1ef-98a9681c607b",
        "src": "__LOCAL_TEMPLATE_ASSET__/ec792701f7705f0c396625e748e8f947c99f57bd.png",
        "top": 831,
        "fill": "rgb(0,0,0)",
        "left": 131,
        "name": "图层 4",
        "type": "image",
        "angle": 0,
        "cropX": 0,
        "cropY": 0,
        "flipX": false,
        "flipY": false,
        "skewX": 0,
        "skewY": 0,
        "width": 530,
        "height": 579,
        "scaleX": 1,
        "scaleY": 1,
        "shadow": null,
        "stroke": null,
        "evented": true,
        "filters": [],
        "opacity": 1,
        "originX": "left",
        "originY": "top",
        "version": "5.5.2",
        "visible": true,
        "fillRule": "nonzero",
        "paintFirst": "fill",
        "selectable": true,
        "crossOrigin": "anonymous",
        "hasControls": true,
        "strokeWidth": 0,
        "strokeLineCap": "butt",
        "strokeUniform": false,
        "strokeLineJoin": "miter",
        "backgroundColor": "",
        "strokeDashArray": null,
        "strokeDashOffset": 0,
        "strokeMiterLimit": 4,
        "globalCompositeOperation": "source-over"
      },
      {
        "id": "4c6d2fbc-0182-445b-a24d-f2892aef135d",
        "src": "__LOCAL_TEMPLATE_ASSET__/246e2724d3afdd5911b1b6f75aa28894573b7c8d.png",
        "top": 812,
        "fill": "rgb(0,0,0)",
        "left": 796,
        "name": "图层 5",
        "type": "image",
        "angle": 0,
        "cropX": 0,
        "cropY": 0,
        "flipX": false,
        "flipY": false,
        "skewX": 0,
        "skewY": 0,
        "width": 283,
        "height": 344,
        "scaleX": 1,
        "scaleY": 1,
        "shadow": null,
        "stroke": null,
        "evented": true,
        "filters": [],
        "opacity": 1,
        "originX": "left",
        "originY": "top",
        "version": "5.5.2",
        "visible": true,
        "fillRule": "nonzero",
        "paintFirst": "fill",
        "selectable": true,
        "crossOrigin": "anonymous",
        "hasControls": true,
        "strokeWidth": 0,
        "strokeLineCap": "butt",
        "strokeUniform": false,
        "strokeLineJoin": "miter",
        "backgroundColor": "",
        "strokeDashArray": null,
        "strokeDashOffset": 0,
        "strokeMiterLimit": 4,
        "globalCompositeOperation": "source-over"
      },
      {
        "id": "92c2c48a-84b1-4403-8dd7-a486d5c47743",
        "src": "__LOCAL_TEMPLATE_ASSET__/f89918fbb2f60f0fefc787c27709b0d590bdccb2.png",
        "top": 1111,
        "fill": "rgb(0,0,0)",
        "left": 605,
        "name": "图层 6",
        "type": "image",
        "angle": 0,
        "cropX": 0,
        "cropY": 0,
        "flipX": false,
        "flipY": false,
        "skewX": 0,
        "skewY": 0,
        "width": 452,
        "height": 234,
        "scaleX": 1,
        "scaleY": 1,
        "shadow": null,
        "stroke": null,
        "evented": true,
        "filters": [],
        "opacity": 1,
        "originX": "left",
        "originY": "top",
        "version": "5.5.2",
        "visible": true,
        "fillRule": "nonzero",
        "paintFirst": "fill",
        "selectable": true,
        "crossOrigin": "anonymous",
        "hasControls": true,
        "strokeWidth": 0,
        "strokeLineCap": "butt",
        "strokeUniform": false,
        "strokeLineJoin": "miter",
        "backgroundColor": "",
        "strokeDashArray": null,
        "strokeDashOffset": 0,
        "strokeMiterLimit": 4,
        "globalCompositeOperation": "source-over"
      },
      {
        "id": "e01206df-c688-435f-ad03-5047c6172dbc",
        "src": "__LOCAL_TEMPLATE_ASSET__/e9eeef3ff9a52965c6d029e0a0187ffdc7f308e2.png",
        "top": 0,
        "fill": "rgb(0,0,0)",
        "left": 0,
        "name": "图层 7",
        "type": "image",
        "angle": 0,
        "cropX": 0,
        "cropY": 0,
        "flipX": false,
        "flipY": false,
        "skewX": 0,
        "skewY": 0,
        "width": 1242,
        "height": 1807,
        "scaleX": 1,
        "scaleY": 1,
        "shadow": null,
        "stroke": null,
        "evented": true,
        "filters": [],
        "opacity": 1,
        "originX": "left",
        "originY": "top",
        "version": "5.5.2",
        "visible": true,
        "fillRule": "nonzero",
        "paintFirst": "fill",
        "selectable": true,
        "crossOrigin": "anonymous",
        "hasControls": true,
        "strokeWidth": 0,
        "strokeLineCap": "butt",
        "strokeUniform": false,
        "strokeLineJoin": "miter",
        "backgroundColor": "",
        "strokeDashArray": null,
        "strokeDashOffset": 0,
        "strokeMiterLimit": 4,
        "globalCompositeOperation": "source-over"
      },
      {
        "id": "3193214c-8264-4045-8a01-85045c185c32",
        "src": "__LOCAL_TEMPLATE_ASSET__/91a3da609bbb4211ff111a96a18d1873045f2b3a.png",
        "top": -49,
        "fill": "rgb(0,0,0)",
        "left": 71,
        "name": "图层 8",
        "type": "image",
        "angle": 0,
        "cropX": 0,
        "cropY": 0,
        "flipX": false,
        "flipY": false,
        "skewX": 0,
        "skewY": 0,
        "width": 1088,
        "height": 670,
        "scaleX": 1,
        "scaleY": 1,
        "shadow": null,
        "stroke": null,
        "evented": true,
        "filters": [],
        "opacity": 1,
        "originX": "left",
        "originY": "top",
        "version": "5.5.2",
        "visible": true,
        "fillRule": "nonzero",
        "paintFirst": "fill",
        "selectable": true,
        "crossOrigin": "anonymous",
        "hasControls": true,
        "strokeWidth": 0,
        "strokeLineCap": "butt",
        "strokeUniform": false,
        "strokeLineJoin": "miter",
        "backgroundColor": "",
        "strokeDashArray": null,
        "strokeDashOffset": 0,
        "strokeMiterLimit": 4,
        "globalCompositeOperation": "source-over"
      },
      {
        "id": "c8c3fbd2-f8f0-4116-95cc-e7dd8446a921",
        "src": "__LOCAL_TEMPLATE_ASSET__/83b622ee245a3883f2b4b21ecd0f7f767389d275.png",
        "top": 1441,
        "fill": "rgb(0,0,0)",
        "left": 95,
        "name": "图层 9",
        "type": "image",
        "angle": 0,
        "cropX": 0,
        "cropY": 0,
        "flipX": false,
        "flipY": false,
        "skewX": 0,
        "skewY": 0,
        "width": 1053,
        "height": 453,
        "scaleX": 1,
        "scaleY": 1,
        "shadow": null,
        "stroke": null,
        "evented": true,
        "filters": [],
        "opacity": 1,
        "originX": "left",
        "originY": "top",
        "version": "5.5.2",
        "visible": true,
        "fillRule": "nonzero",
        "paintFirst": "fill",
        "selectable": true,
        "crossOrigin": "anonymous",
        "hasControls": true,
        "strokeWidth": 0,
        "strokeLineCap": "butt",
        "strokeUniform": false,
        "strokeLineJoin": "miter",
        "backgroundColor": "",
        "strokeDashArray": null,
        "strokeDashOffset": 0,
        "strokeMiterLimit": 4,
        "globalCompositeOperation": "source-over"
      },
      {
        "id": "5139c652-8be5-4084-a91f-50f275ac3294",
        "src": "__LOCAL_TEMPLATE_ASSET__/1c4f3e07f03a8fa2d4c4a3794c204481c30f3126.png",
        "top": 1515,
        "fill": "rgb(0,0,0)",
        "left": 152,
        "name": "图层 10",
        "type": "image",
        "angle": 0,
        "cropX": 0,
        "cropY": 0,
        "flipX": false,
        "flipY": false,
        "skewX": 0,
        "skewY": 0,
        "width": 940,
        "height": 305,
        "scaleX": 1,
        "scaleY": 1,
        "shadow": null,
        "stroke": null,
        "evented": true,
        "filters": [],
        "opacity": 1,
        "originX": "left",
        "originY": "top",
        "version": "5.5.2",
        "visible": true,
        "fillRule": "nonzero",
        "paintFirst": "fill",
        "selectable": true,
        "crossOrigin": "anonymous",
        "hasControls": true,
        "strokeWidth": 0,
        "strokeLineCap": "butt",
        "strokeUniform": false,
        "strokeLineJoin": "miter",
        "backgroundColor": "",
        "strokeDashArray": null,
        "strokeDashOffset": 0,
        "strokeMiterLimit": 4,
        "globalCompositeOperation": "source-over"
      },
      {
        "id": "ba38e491-f26d-4488-953e-52194d3f1b53",
        "src": "__LOCAL_TEMPLATE_ASSET__/0d6b5ce7a023203fd940da86b3a6bf280da0af5e.png",
        "top": 1400,
        "fill": "rgb(0,0,0)",
        "left": 386,
        "name": "图层 11",
        "type": "image",
        "angle": 0,
        "cropX": 0,
        "cropY": 0,
        "flipX": false,
        "flipY": false,
        "skewX": 0,
        "skewY": 0,
        "width": 466,
        "height": 119,
        "scaleX": 1,
        "scaleY": 1,
        "shadow": null,
        "stroke": null,
        "evented": true,
        "filters": [],
        "opacity": 1,
        "originX": "left",
        "originY": "top",
        "version": "5.5.2",
        "visible": true,
        "fillRule": "nonzero",
        "paintFirst": "fill",
        "selectable": true,
        "crossOrigin": "anonymous",
        "hasControls": true,
        "strokeWidth": 0,
        "strokeLineCap": "butt",
        "strokeUniform": false,
        "strokeLineJoin": "miter",
        "backgroundColor": "",
        "strokeDashArray": null,
        "strokeDashOffset": 0,
        "strokeMiterLimit": 4,
        "globalCompositeOperation": "source-over"
      },
      {
        "id": "c157327b-1996-418e-a1ca-9c83704809f1",
        "src": "__LOCAL_TEMPLATE_ASSET__/96b6d4ce2dcb69dee769a256da88052f1263dd32.png",
        "top": 1943,
        "fill": "rgb(0,0,0)",
        "left": 768,
        "name": "图层 12",
        "type": "image",
        "angle": 0,
        "cropX": 0,
        "cropY": 0,
        "flipX": false,
        "flipY": false,
        "skewX": 0,
        "skewY": 0,
        "width": 211,
        "height": 211,
        "scaleX": 1,
        "scaleY": 1,
        "shadow": null,
        "stroke": null,
        "evented": true,
        "filters": [],
        "opacity": 1,
        "originX": "left",
        "originY": "top",
        "version": "5.5.2",
        "visible": true,
        "fillRule": "nonzero",
        "paintFirst": "fill",
        "selectable": true,
        "crossOrigin": "anonymous",
        "hasControls": true,
        "strokeWidth": 0,
        "strokeLineCap": "butt",
        "strokeUniform": false,
        "strokeLineJoin": "miter",
        "backgroundColor": "",
        "strokeDashArray": null,
        "strokeDashOffset": 0,
        "strokeMiterLimit": 4,
        "globalCompositeOperation": "source-over"
      },
      {
        "id": "7e5be4d1-434f-46ae-94dc-3941d50d5a5b",
        "top": 2008.8474,
        "fill": "rgb(253.0008, 254.00039999999998, 254.00039999999998)",
        "left": 131,
        "name": "扫码二维码了解更多详情 联系电话：027-88888888  ",
        "path": null,
        "text": "扫码二维码了解更多详情\n联系电话：027-88888888\n\n",
        "type": "textbox",
        "angle": 0,
        "flipX": false,
        "flipY": false,
        "skewX": 0,
        "skewY": 0,
        "width": 542.2919,
        "height": 187.3088,
        "scaleX": 1,
        "scaleY": 1,
        "shadow": "",
        "stroke": null,
        "styles": [],
        "evented": true,
        "opacity": 1,
        "originX": "left",
        "originY": "top",
        "version": "5.5.2",
        "visible": true,
        "editable": true,
        "fillRule": "nonzero",
        "fontSize": 37,
        "minWidth": 20,
        "overline": false,
        "pathSide": "left",
        "direction": "ltr",
        "fontStyle": "normal",
        "pathAlign": "baseline",
        "textAlign": "left",
        "underline": false,
        "fontFamily": "站酷快乐体",
        "fontWeight": "normal",
        "lineHeight": 1.16,
        "paintFirst": "fill",
        "selectable": true,
        "charSpacing": 0,
        "hasControls": true,
        "linethrough": false,
        "strokeWidth": 1,
        "strokeLineCap": "butt",
        "strokeUniform": false,
        "strokeLineJoin": "miter",
        "backgroundColor": "",
        "pathStartOffset": 0,
        "splitByGrapheme": true,
        "strokeDashArray": null,
        "strokeDashOffset": 0,
        "strokeMiterLimit": 4,
        "textBackgroundColor": "",
        "globalCompositeOperation": "source-over"
      },
      {
        "id": "bb6703d1-7237-49a1-9870-27c5db0aa94d",
        "src": "__LOCAL_TEMPLATE_ASSET__/c243e3d186b69c1a2e5381c41e02c22105902c22.png",
        "top": 440,
        "fill": "rgb(0,0,0)",
        "left": 235,
        "name": "图层 14",
        "type": "image",
        "angle": 0,
        "cropX": 0,
        "cropY": 0,
        "flipX": false,
        "flipY": false,
        "skewX": 0,
        "skewY": 0,
        "width": 771,
        "height": 82,
        "scaleX": 1,
        "scaleY": 1,
        "shadow": null,
        "stroke": null,
        "evented": true,
        "filters": [],
        "opacity": 1,
        "originX": "left",
        "originY": "top",
        "version": "5.5.2",
        "visible": true,
        "fillRule": "nonzero",
        "paintFirst": "fill",
        "selectable": true,
        "crossOrigin": "anonymous",
        "hasControls": true,
        "strokeWidth": 0,
        "strokeLineCap": "butt",
        "strokeUniform": false,
        "strokeLineJoin": "miter",
        "backgroundColor": "",
        "strokeDashArray": null,
        "strokeDashOffset": 0,
        "strokeMiterLimit": 4,
        "globalCompositeOperation": "source-over"
      },
      {
        "id": "41a30774-b1aa-433f-841c-64682d5cc5ab",
        "top": 1578.5421,
        "fill": "rgb(103.9992, 59.99895, 39.9993)",
        "left": 206.5763,
        "name": "1.品牌保证：品牌保险官方平台，便捷理赔 2.特惠惊喜：618活动福利，尊享免息分期服务 3.福利好礼：好券每月派送，洗车优惠享不停  ",
        "path": null,
        "text": "1.品牌保证：品牌保险官方平台，便捷理赔\r2.特惠惊喜：618活动福利，尊享免息分期服务\r3.福利好礼：好券每月派送，洗车优惠享不停\r\r",
        "type": "textbox",
        "angle": 0,
        "flipX": false,
        "flipY": false,
        "skewX": 0,
        "skewY": 0,
        "width": 829.376,
        "height": 138.8092,
        "scaleX": 1,
        "scaleY": 1,
        "shadow": "",
        "stroke": null,
        "styles": [],
        "evented": true,
        "opacity": 1,
        "originX": "left",
        "originY": "top",
        "version": "5.5.2",
        "visible": true,
        "editable": true,
        "fillRule": "nonzero",
        "fontSize": 37,
        "minWidth": 20,
        "overline": false,
        "pathSide": "left",
        "direction": "ltr",
        "fontStyle": "normal",
        "pathAlign": "baseline",
        "textAlign": "left",
        "underline": false,
        "fontFamily": "站酷快乐体",
        "fontWeight": "normal",
        "lineHeight": 1.16,
        "paintFirst": "fill",
        "selectable": true,
        "charSpacing": 0,
        "hasControls": true,
        "linethrough": false,
        "strokeWidth": 1,
        "strokeLineCap": "butt",
        "strokeUniform": false,
        "strokeLineJoin": "miter",
        "backgroundColor": "",
        "pathStartOffset": 0,
        "splitByGrapheme": true,
        "strokeDashArray": null,
        "strokeDashOffset": 0,
        "strokeMiterLimit": 4,
        "textBackgroundColor": "",
        "globalCompositeOperation": "source-over"
      },
      {
        "id": "a88fcd9d-6bd0-4bf9-9350-9c5e69748a80",
        "top": 1425,
        "fill": "rgb(255, 255, 255)",
        "left": 496,
        "name": "产品特色  ",
        "path": null,
        "text": "产品特色\r\r",
        "type": "textbox",
        "angle": 0,
        "flipX": false,
        "flipY": false,
        "skewX": 0,
        "skewY": 0,
        "width": 244,
        "height": 139.1256,
        "scaleX": 1,
        "scaleY": 1,
        "shadow": "",
        "stroke": null,
        "styles": [],
        "evented": true,
        "opacity": 1,
        "originX": "left",
        "originY": "top",
        "version": "5.5.2",
        "visible": true,
        "editable": true,
        "fillRule": "nonzero",
        "fontSize": 57,
        "minWidth": 20,
        "overline": false,
        "pathSide": "left",
        "direction": "ltr",
        "fontStyle": "normal",
        "pathAlign": "baseline",
        "textAlign": "left",
        "underline": false,
        "fontFamily": "站酷快乐体",
        "fontWeight": "normal",
        "lineHeight": 1.16,
        "paintFirst": "fill",
        "selectable": true,
        "charSpacing": 0,
        "hasControls": true,
        "linethrough": false,
        "strokeWidth": 1,
        "strokeLineCap": "butt",
        "strokeUniform": false,
        "strokeLineJoin": "miter",
        "backgroundColor": "",
        "pathStartOffset": 0,
        "splitByGrapheme": true,
        "strokeDashArray": null,
        "strokeDashOffset": 0,
        "strokeMiterLimit": 4,
        "textBackgroundColor": "",
        "globalCompositeOperation": "source-over"
      },
      {
        "id": "8f72f217-854d-4931-9c40-91f1c3f83fb0",
        "top": 456,
        "fill": "rgb(255, 255, 255)",
        "left": 338,
        "name": "618特惠车险福利活动  ",
        "path": null,
        "text": "618特惠车险福利活动\r\r",
        "type": "textbox",
        "angle": 0,
        "flipX": false,
        "flipY": false,
        "skewX": 0,
        "skewY": 0,
        "width": 489,
        "height": 119.5992,
        "scaleX": 1,
        "scaleY": 1,
        "shadow": "",
        "stroke": null,
        "styles": [],
        "evented": true,
        "opacity": 1,
        "originX": "left",
        "originY": "top",
        "version": "5.5.2",
        "visible": true,
        "editable": true,
        "fillRule": "nonzero",
        "fontSize": 49,
        "minWidth": 20,
        "overline": false,
        "pathSide": "left",
        "direction": "ltr",
        "fontStyle": "normal",
        "pathAlign": "baseline",
        "textAlign": "left",
        "underline": false,
        "fontFamily": "站酷快乐体",
        "fontWeight": "normal",
        "lineHeight": 1.16,
        "paintFirst": "fill",
        "selectable": true,
        "charSpacing": 0,
        "hasControls": true,
        "linethrough": false,
        "strokeWidth": 1,
        "strokeLineCap": "butt",
        "strokeUniform": false,
        "strokeLineJoin": "miter",
        "backgroundColor": "",
        "pathStartOffset": 0,
        "splitByGrapheme": true,
        "strokeDashArray": null,
        "strokeDashOffset": 0,
        "strokeMiterLimit": 4,
        "textBackgroundColor": "",
        "globalCompositeOperation": "source-over"
      },
      {
        "id": "8792c562-efbd-433e-baee-4e953a160ede",
        "top": 50.729,
        "fill": "rgb(255, 255, 255)",
        "left": 216.2686,
        "name": "车主好权益 年中享福利  ",
        "path": null,
        "text": "车主好权益\r年中享福利\r\r",
        "type": "textbox",
        "angle": 0,
        "flipX": false,
        "flipY": false,
        "skewX": 0,
        "skewY": 0,
        "width": 962.4788,
        "height": 652.7784,
        "scaleX": 0.8401,
        "scaleY": 0.8401,
        "shadow": "",
        "stroke": null,
        "styles": [],
        "evented": true,
        "opacity": 1,
        "originX": "left",
        "originY": "top",
        "version": "5.5.2",
        "visible": true,
        "editable": true,
        "fillRule": "nonzero",
        "fontSize": 174,
        "minWidth": 20,
        "overline": false,
        "pathSide": "left",
        "direction": "ltr",
        "fontStyle": "normal",
        "pathAlign": "baseline",
        "textAlign": "left",
        "underline": false,
        "fontFamily": "站酷快乐体",
        "fontWeight": "normal",
        "lineHeight": 1.16,
        "paintFirst": "fill",
        "selectable": true,
        "charSpacing": 0,
        "hasControls": true,
        "linethrough": false,
        "strokeWidth": 1,
        "strokeLineCap": "butt",
        "strokeUniform": false,
        "strokeLineJoin": "miter",
        "backgroundColor": "",
        "pathStartOffset": 0,
        "splitByGrapheme": true,
        "strokeDashArray": null,
        "strokeDashOffset": 0,
        "strokeMiterLimit": 4,
        "textBackgroundColor": "",
        "globalCompositeOperation": "source-over"
      }
    ],
    "version": "5.5.2",
    "clipPath": {
      "rx": 0,
      "ry": 0,
      "top": 0,
      "fill": "rgba(255,255,255,1)",
      "left": 0,
      "type": "rect",
      "angle": 0,
      "flipX": false,
      "flipY": false,
      "skewX": 0,
      "skewY": 0,
      "width": 1242,
      "height": 2208,
      "scaleX": 1,
      "scaleY": 1,
      "shadow": null,
      "stroke": null,
      "evented": true,
      "opacity": 1,
      "originX": "left",
      "originY": "top",
      "version": "5.5.2",
      "visible": true,
      "fillRule": "nonzero",
      "paintFirst": "fill",
      "selectable": true,
      "hasControls": true,
      "strokeWidth": 0,
      "strokeLineCap": "butt",
      "strokeUniform": false,
      "strokeLineJoin": "miter",
      "backgroundColor": "",
      "strokeDashArray": null,
      "strokeDashOffset": 0,
      "strokeMiterLimit": 4,
      "globalCompositeOperation": "source-over"
    }
  }
}