{
  "id": 121,
  "name": "商品模板",
  "desc": null,
  "categoryId": 8,
  "categoryName": "定制商品",
  "width": 1000,
  "height": 1000,
  "json": {
    "objects": [
      {
        "id": "workspace",
        "rx": 0,
        "ry": 0,
        "top": 0,
        "fill": "rgba(255,255,255,1)",
        "left": 0,
        "type": "rect",
        "angle": 0,
        "flipX": false,
        "flipY": false,
        "skewX": 0,
        "skewY": 0,
        "width": 1000,
        "height": 1000,
        "scaleX": 1,
        "scaleY": 1,
        "shadow": null,
        "stroke": null,
        "evented": false,
        "opacity": 1,
        "originX": "left",
        "originY": "top",
        "version": "5.5.2",
        "visible": true,
        "fillRule": "nonzero",
        "paintFirst": "fill",
        "selectable": false,
        "hasControls": false,
        "strokeWidth": 0,
        "strokeLineCap": "butt",
        "strokeUniform": false,
        "strokeLineJoin": "miter",
        "backgroundColor": "",
        "strokeDashArray": null,
        "strokeDashOffset": 0,
        "strokeMiterLimit": 4,
        "globalCompositeOperation": "source-over"
      },
      {
        "id": "3bf2cfa4-1e30-4c6f-b407-cc0adcd094cd",
        "src": "__LOCAL_TEMPLATE_ASSET__/6361f5615fc826975db10e91dc6821fa473af44f.png",
        "top": 205.3239,
        "fill": "rgb(0,0,0)",
        "left": 166.6046,
        "type": "image",
        "angle": 0,
        "cropX": 0,
        "cropY": 0,
        "flipX": false,
        "flipY": false,
        "skewX": 0,
        "skewY": 0,
        "width": 2000,
        "height": 2000,
        "scaleX": 0.3136,
        "scaleY": 0.3136,
        "shadow": null,
        "stroke": null,
        "evented": true,
        "filters": [],
        "opacity": 1,
        "originX": "left",
        "originY": "top",
        "version": "5.5.2",
        "visible": true,
        "fillRule": "nonzero",
        "paintFirst": "fill",
        "selectable": true,
        "crossOrigin": "anonymous",
        "hasControls": true,
        "strokeWidth": 0,
        "strokeLineCap": "butt",
        "strokeUniform": false,
        "strokeLineJoin": "miter",
        "backgroundColor": "",
        "strokeDashArray": null,
        "strokeDashOffset": 0,
        "strokeMiterLimit": 4,
        "globalCompositeOperation": "source-over"
      },
      {
        "id": "d70d5e73-08b2-49fb-8711-77beed5d19ca",
        "src": "__LOCAL_TEMPLATE_ASSET__/52c4d0333368bf150c07ee1a944b96c7408cf8b4.png",
        "top": 0,
        "fill": "rgb(0,0,0)",
        "left": 0,
        "name": "clipImg",
        "type": "image",
        "angle": 0,
        "cropX": 0,
        "cropY": 0,
        "flipX": false,
        "flipY": false,
        "skewX": 0,
        "skewY": 0,
        "width": 512,
        "height": 512,
        "scaleX": 1.9531,
        "scaleY": 1.9531,
        "shadow": null,
        "stroke": null,
        "evented": false,
        "filters": [],
        "opacity": 1,
        "originX": "left",
        "originY": "top",
        "version": "5.5.2",
        "visible": true,
        "fillRule": "nonzero",
        "paintFirst": "fill",
        "selectable": false,
        "crossOrigin": "anonymous",
        "hasControls": false,
        "strokeWidth": 0,
        "strokeLineCap": "butt",
        "strokeUniform": false,
        "strokeLineJoin": "miter",
        "backgroundColor": "",
        "strokeDashArray": null,
        "strokeDashOffset": 0,
        "strokeMiterLimit": 4,
        "globalCompositeOperation": "source-over"
      }
    ],
    "version": "5.5.2",
    "clipPath": {
      "rx": 0,
      "ry": 0,
      "top": 0,
      "fill": "rgba(255,255,255,1)",
      "left": 0,
      "type": "rect",
      "angle": 0,
      "flipX": false,
      "flipY": false,
      "skewX": 0,
      "skewY": 0,
      "width": 1000,
      "height": 1000,
      "scaleX": 1,
      "scaleY": 1,
      "shadow": null,
      "stroke": null,
      "evented": true,
      "opacity": 1,
      "originX": "left",
      "originY": "top",
      "version": "5.5.2",
      "visible": true,
      "fillRule": "nonzero",
      "paintFirst": "fill",
      "selectable": true,
      "hasControls": true,
      "strokeWidth": 0,
      "strokeLineCap": "butt",
      "strokeUniform": false,
      "strokeLineJoin": "miter",
      "backgroundColor": "",
      "strokeDashArray": null,
      "strokeDashOffset": 0,
      "strokeMiterLimit": 4,
      "globalCompositeOperation": "source-over"
    }
  }
}